x_make_test3_x/__init__.py
x_make_test3_x/x_cls_make_test3_x.py
x_make_test3_x-10.0.0.dist-info/METADATA
x_make_test3_x-10.0.0.dist-info/WHEEL
x_make_test3_x-10.0.0.dist-info/top_level.txt
x_make_test3_x-10.0.0.dist-info/RECORD
